up_dn_cntr.v
/*
Author: Mayank Parasar
email-id: mparasar3@gatech.edu
Description:
In this file I am trying to implement
an up/down counter...
*/
// Trivia: Inputs are always wires..
// though can be driven by reg or wire externally..
// Output can be reg or wire, but always connected
// as wires to the extrnal world..

/*Declaring and defining the ports of 'counter' module...*/
module up_dn_cntr (
input wire clk, // clock
input wire rst, // reset
input wire sense, // for up/down signal..
				  // 1: up; 0:down
output reg [3:0] cntr // output of the counter at anytime
);

/*Define the logic of the counter here..*/
/*It should be a saturating counter..
Otherwise the default dehaviour is rollong over.. */

always @(posedge clk or posedge rst) begin
	if (rst) begin
		// reset
		cntr <= 4'b0000;
	end
	else if (sense == 1'b1) begin
		if (cntr == 4'b1111) 
			cntr <= 4'b1111;
		else 
			cntr <= cntr + 1'b1;
	end else if (sense == 1'b0) begin
		if (cntr == 4'b0000) 
			cntr <= 4'b0000;
		else 
			cntr <= cntr - 1'b1;
	end
end

endmodule

gen_up_dn_cntr.v


// This is the top level module to generate 
// 10 up-down counter...

`include "up_dn_cntr.v"

// Currently generating only 8 up_dwn counter..
// such  that output of each of them is connected
// as input of next counter..
// since input necessarily needed to be wires.. we
// have to tap outpu of each module as wires..
module gen_up_dn_cntr(
input wire 			clk, // it gets the clock
// input wire 	[3:0] 	data_in, 
input wire 			reset,
input wire 			sense,
output wire [31:0] 	data_out // this is the final output
						     // of last counter...
);

// Define intermediate wires for connections
// as described above here...
// wire [3:0] out_1;
// wire [3:0] out_2;
// wire [3:0] out_3;
// wire [3:0] out_4;
// wire [3:0] out_5;
// wire [3:0] out_6;
// wire [3:0] out_7;
// wire [27:0] data;

generate
	genvar i;
	for (i = 0; i < 8; i = i + 1) begin:CNTR
		up_dn_cntr U (
			.clk 	(clk),
			.rst 	(reset),
			.sense 	(sense),
			.cntr 	(data_out[((i*4) + 3): (i*4)])
			);
	end
endgenerate

endmodule

gen_up_dn_cntr_tb.v
// This is a test bench for 'gen_up_dn_cntr.v' file
// this will give stimulus to it DUT

`include "gen_up_dn_cntr.v"
module gen_up_dn_cntr_tb(); // again note that it has no in/op ports..

// What signals need to go to DUT: "gen_up_dn_cntr"
reg clk;
reg rst;
reg sense;
wire [31:0] out; // wire to tap the output of DUT...

// initializing the variables here...
initial begin
	$dumpfile("gen_up_dn_cntr.vcd");
	$dumpvars(0, gen_up_dn_cntr_tb);
	clk <= 0;
	rst <= 0;
	#2 rst <= 1; // asserting reset
	#4 rst <= 0;  // de-asserting reset
	sense <= 1; // counting up...
	#10 sense <= 0; // counting down...

	#15 $finish;
end

initial #1 forever clk = #1 ~clk;

// Instantiate your DUT here...
gen_up_dn_cntr cnt(
.clk 		(clk),
.reset 		(rst),
.sense 		(sense),
.data_out 	(out)
);

// Print your stats here from the circuit...
initial begin
	$display("+--------------------------------------------------------------------------+");
	$display("|clock|reset|sense|data_out|");
	$display("+--------------------------------------------------------------------------+");
	$monitor("|  %h  |  %h  |  %h  |  %b  |",
				clk, rst, sense, out);
end

endmodule

gen_up_dn_cntr.vcd
$date
	Sun Jan 22 20:41:20 2017
$end
$version
	Icarus Verilog
$end
$timescale
	1s
$end
$scope module gen_up_dn_cntr_tb $end
$var wire 32 ! out [31:0] $end
$var reg 1 " clk $end
$var reg 1 # rst $end
$var reg 1 $ sense $end
$scope module cnt $end
$var wire 1 % clk $end
$var wire 32 & data_out [31:0] $end
$var wire 1 ' reset $end
$var wire 1 ( sense $end
$scope begin CNTR[0] $end
$scope module U $end
$var wire 1 % clk $end
$var wire 1 ' rst $end
$var wire 1 ( sense $end
$var reg 4 ) cntr [3:0] $end
$upscope $end
$upscope $end
$scope begin CNTR[1] $end
$scope module U $end
$var wire 1 % clk $end
$var wire 1 ' rst $end
$var wire 1 ( sense $end
$var reg 4 * cntr [3:0] $end
$upscope $end
$upscope $end
$scope begin CNTR[2] $end
$scope module U $end
$var wire 1 % clk $end
$var wire 1 ' rst $end
$var wire 1 ( sense $end
$var reg 4 + cntr [3:0] $end
$upscope $end
$upscope $end
$scope begin CNTR[3] $end
$scope module U $end
$var wire 1 % clk $end
$var wire 1 ' rst $end
$var wire 1 ( sense $end
$var reg 4 , cntr [3:0] $end
$upscope $end
$upscope $end
$scope begin CNTR[4] $end
$scope module U $end
$var wire 1 % clk $end
$var wire 1 ' rst $end
$var wire 1 ( sense $end
$var reg 4 - cntr [3:0] $end
$upscope $end
$upscope $end
$scope begin CNTR[5] $end
$scope module U $end
$var wire 1 % clk $end
$var wire 1 ' rst $end
$var wire 1 ( sense $end
$var reg 4 . cntr [3:0] $end
$upscope $end
$upscope $end
$scope begin CNTR[6] $end
$scope module U $end
$var wire 1 % clk $end
$var wire 1 ' rst $end
$var wire 1 ( sense $end
$var reg 4 / cntr [3:0] $end
$upscope $end
$upscope $end
$scope begin CNTR[7] $end
$scope module U $end
$var wire 1 % clk $end
$var wire 1 ' rst $end
$var wire 1 ( sense $end
$var reg 4 0 cntr [3:0] $end
$upscope $end
$upscope $end
$upscope $end
$upscope $end
$enddefinitions $end
#0
$dumpvars
bx 0
bx /
bx .
bx -
bx ,
bx +
bx *
bx )
x(
0'
bx &
0%
x$
0#
0"
bx !
$end
#2
b0 0
b0 /
b0 .
b0 -
b0 ,
b0 +
b0 *
b0 )
b0 !
b0 &
1#
1'
1"
1%
#3
0"
0%
#4
1"
1%
#5
0"
0%
#6
1$
1(
0#
0'
1"
1%
#7
0"
0%
#8
b1 )
b1 *
b1 +
b1 ,
b1 -
b1 .
b1 /
b1 0
b10001000100010001000100010001 !
b10001000100010001000100010001 &
1"
1%
#9
0"
0%
#10
b10 0
b10 /
b10 .
b10 -
b10 ,
b10 +
b10 *
b10 )
b100010001000100010001000100010 !
b100010001000100010001000100010 &
1"
1%
#11
0"
0%
#12
b11 )
b11 *
b11 +
b11 ,
b11 -
b11 .
b11 /
b11 0
b110011001100110011001100110011 !
b110011001100110011001100110011 &
1"
1%
#13
0"
0%
#14
b100 0
b100 /
b100 .
b100 -
b100 ,
b100 +
b100 *
b100 )
b1000100010001000100010001000100 !
b1000100010001000100010001000100 &
1"
1%
#15
0"
0%
#16
b101 )
b101 *
b101 +
b101 ,
b101 -
b101 .
b101 /
b101 0
b1010101010101010101010101010101 !
b1010101010101010101010101010101 &
0$
0(
1"
1%
#17
0"
0%
#18
b100 0
b100 /
b100 .
b100 -
b100 ,
b100 +
b100 *
b100 )
b1000100010001000100010001000100 !
b1000100010001000100010001000100 &
1"
1%
#19
0"
0%
#20
b11 )
b11 *
b11 +
b11 ,
b11 -
b11 .
b11 /
b11 0
b110011001100110011001100110011 !
b110011001100110011001100110011 &
1"
1%
#21
0"
0%
#22
b10 0
b10 /
b10 .
b10 -
b10 ,
b10 +
b10 *
b10 )
b100010001000100010001000100010 !
b100010001000100010001000100010 &
1"
1%
#23
0"
0%
#24
b1 )
b1 *
b1 +
b1 ,
b1 -
b1 .
b1 /
b1 0
b10001000100010001000100010001 !
b10001000100010001000100010001 &
1"
1%
#25
0"
0%
#26
b0 0
b0 /
b0 .
b0 -
b0 ,
b0 +
b0 *
b0 )
b0 !
b0 &
1"
1%
